{"race":"hd17","race_label":"House District 17","reporting":"Precincts 2203 of 2204 Reporting (Precincts Partially Reported: 1/2204)","candidates":[{"key":"CYNTHIA D BORREGO","name":"Cynthia D Borrego","party":"D","color":"#2166ac"},{"key":"STACEY DEANNE RICH","name":"Stacey Deanne Rich","party":"R","color":"#b2182b"}],"party_labels":{"R":"Republican","D":"Democrat"},"results":{"Bernalillo|2":{"county":"Bernalillo","precinct":2,"counts":{"STACEY DEANNE RICH":68,"CYNTHIA D BORREGO":151},"suppressed":[],"party_totals":{"R":68,"D":151},"total":219,"winner":{"R":"STACEY DEANNE RICH","D":"CYNTHIA D BORREGO"},"margin":{"R":1.0,"D":1.0}},"Bernalillo|3":{"county":"Bernalillo","precinct":3,"counts":{"STACEY DEANNE RICH":53,"CYNTHIA D BORREGO":47},"suppressed":[],"party_totals":{"R":53,"D":47},"total":100,"winner":{"R":"STACEY DEANNE RICH","D":"CYNTHIA D BORREGO"},"margin":{"R":1.0,"D":1.0}},"Bernalillo|69":{"county":"Bernalillo","precinct":69,"counts":{"STACEY DEANNE RICH":45,"CYNTHIA D BORREGO":128},"suppressed":[],"party_totals":{"R":45,"D":128},"total":173,"winner":{"R":"STACEY DEANNE RICH","D":"CYNTHIA D BORREGO"},"margin":{"R":1.0,"D":1.0}},"Bernalillo|78":{"county":"Bernalillo","precinct":78,"counts":{"STACEY DEANNE RICH":49,"CYNTHIA D BORREGO":77},"suppressed":[],"party_totals":{"R":49,"D":77},"total":126,"winner":{"R":"STACEY DEANNE RICH","D":"CYNTHIA D BORREGO"},"margin":{"R":1.0,"D":1.0}},"Bernalillo|79":{"county":"Bernalillo","precinct":79,"counts":{"STACEY DEANNE RICH":45,"CYNTHIA D BORREGO":76},"suppressed":[],"party_totals":{"R":45,"D":76},"total":121,"winner":{"R":"STACEY DEANNE RICH","D":"CYNTHIA D BORREGO"},"margin":{"R":1.0,"D":1.0}},"Bernalillo|82":{"county":"Bernalillo","precinct":82,"counts":{"STACEY DEANNE RICH":80,"CYNTHIA D BORREGO":130},"suppressed":[],"party_totals":{"R":80,"D":130},"total":210,"winner":{"R":"STACEY DEANNE RICH","D":"CYNTHIA D BORREGO"},"margin":{"R":1.0,"D":1.0}},"Bernalillo|83":{"county":"Bernalillo","precinct":83,"counts":{"STACEY DEANNE RICH":32,"CYNTHIA D BORREGO":134},"suppressed":[],"party_totals":{"R":32,"D":134},"total":166,"winner":{"R":"STACEY DEANNE RICH","D":"CYNTHIA D BORREGO"},"margin":{"R":1.0,"D":1.0}},"Bernalillo|84":{"county":"Bernalillo","precinct":84,"counts":{"STACEY DEANNE RICH":63,"CYNTHIA D BORREGO":89},"suppressed":[],"party_totals":{"R":63,"D":89},"total":152,"winner":{"R":"STACEY DEANNE RICH","D":"CYNTHIA D BORREGO"},"margin":{"R":1.0,"D":1.0}},"Bernalillo|89":{"county":"Bernalillo","precinct":89,"counts":{"STACEY DEANNE RICH":38,"CYNTHIA D BORREGO":96},"suppressed":[],"party_totals":{"R":38,"D":96},"total":134,"winner":{"R":"STACEY DEANNE RICH","D":"CYNTHIA D BORREGO"},"margin":{"R":1.0,"D":1.0}},"Bernalillo|100":{"county":"Bernalillo","precinct":100,"counts":{"STACEY DEANNE RICH":55,"CYNTHIA D BORREGO":102},"suppressed":[],"party_totals":{"R":55,"D":102},"total":157,"winner":{"R":"STACEY DEANNE RICH","D":"CYNTHIA D BORREGO"},"margin":{"R":1.0,"D":1.0}},"Bernalillo|114":{"county":"Bernalillo","precinct":114,"counts":{"STACEY DEANNE RICH":85,"CYNTHIA D BORREGO":129},"suppressed":[],"party_totals":{"R":85,"D":129},"total":214,"winner":{"R":"STACEY DEANNE RICH","D":"CYNTHIA D BORREGO"},"margin":{"R":1.0,"D":1.0}},"Bernalillo|116":{"county":"Bernalillo","precinct":116,"counts":{"STACEY DEANNE RICH":73,"CYNTHIA D BORREGO":125},"suppressed":[],"party_totals":{"R":73,"D":125},"total":198,"winner":{"R":"STACEY DEANNE RICH","D":"CYNTHIA D BORREGO"},"margin":{"R":1.0,"D":1.0}},"Bernalillo|171":{"county":"Bernalillo","precinct":171,"counts":{"STACEY DEANNE RICH":28,"CYNTHIA D BORREGO":96},"suppressed":[],"party_totals":{"R":28,"D":96},"total":124,"winner":{"R":"STACEY DEANNE RICH","D":"CYNTHIA D BORREGO"},"margin":{"R":1.0,"D":1.0}},"Bernalillo|172":{"county":"Bernalillo","precinct":172,"counts":{"STACEY DEANNE RICH":34,"CYNTHIA D BORREGO":73},"suppressed":[],"party_totals":{"R":34,"D":73},"total":107,"winner":{"R":"STACEY DEANNE RICH","D":"CYNTHIA D BORREGO"},"margin":{"R":1.0,"D":1.0}},"Bernalillo|173":{"county":"Bernalillo","precinct":173,"counts":{"STACEY DEANNE RICH":35,"CYNTHIA D BORREGO":94},"suppressed":[],"party_totals":{"R":35,"D":94},"total":129,"winner":{"R":"STACEY DEANNE RICH","D":"CYNTHIA D BORREGO"},"margin":{"R":1.0,"D":1.0}},"Bernalillo|174":{"county":"Bernalillo","precinct":174,"counts":{"STACEY DEANNE RICH":56,"CYNTHIA D BORREGO":109},"suppressed":[],"party_totals":{"R":56,"D":109},"total":165,"winner":{"R":"STACEY DEANNE RICH","D":"CYNTHIA D BORREGO"},"margin":{"R":1.0,"D":1.0}},"Bernalillo|179":{"county":"Bernalillo","precinct":179,"counts":{"STACEY DEANNE RICH":54,"CYNTHIA D BORREGO":88},"suppressed":[],"party_totals":{"R":54,"D":88},"total":142,"winner":{"R":"STACEY DEANNE RICH","D":"CYNTHIA D BORREGO"},"margin":{"R":1.0,"D":1.0}},"Bernalillo|200":{"county":"Bernalillo","precinct":200,"counts":{"STACEY DEANNE RICH":39,"CYNTHIA D BORREGO":55},"suppressed":[],"party_totals":{"R":39,"D":55},"total":94,"winner":{"R":"STACEY DEANNE RICH","D":"CYNTHIA D BORREGO"},"margin":{"R":1.0,"D":1.0}},"Bernalillo|202":{"county":"Bernalillo","precinct":202,"counts":{"STACEY DEANNE RICH":70,"CYNTHIA D BORREGO":104},"suppressed":[],"party_totals":{"R":70,"D":104},"total":174,"winner":{"R":"STACEY DEANNE RICH","D":"CYNTHIA D BORREGO"},"margin":{"R":1.0,"D":1.0}},"Bernalillo|203":{"county":"Bernalillo","precinct":203,"counts":{"STACEY DEANNE RICH":54,"CYNTHIA D BORREGO":98},"suppressed":[],"party_totals":{"R":54,"D":98},"total":152,"winner":{"R":"STACEY DEANNE RICH","D":"CYNTHIA D BORREGO"},"margin":{"R":1.0,"D":1.0}},"Bernalillo|222":{"county":"Bernalillo","precinct":222,"counts":{"STACEY DEANNE RICH":67,"CYNTHIA D BORREGO":130},"suppressed":[],"party_totals":{"R":67,"D":130},"total":197,"winner":{"R":"STACEY DEANNE RICH","D":"CYNTHIA D BORREGO"},"margin":{"R":1.0,"D":1.0}},"Bernalillo|232":{"county":"Bernalillo","precinct":232,"counts":{"STACEY DEANNE RICH":31,"CYNTHIA D BORREGO":114},"suppressed":[],"party_totals":{"R":31,"D":114},"total":145,"winner":{"R":"STACEY DEANNE RICH","D":"CYNTHIA D BORREGO"},"margin":{"R":1.0,"D":1.0}},"Bernalillo|248":{"county":"Bernalillo","precinct":248,"counts":{"STACEY DEANNE RICH":7,"CYNTHIA D BORREGO":30},"suppressed":[],"party_totals":{"R":7,"D":30},"total":37,"winner":{"R":"STACEY DEANNE RICH","D":"CYNTHIA D BORREGO"},"margin":{"R":1.0,"D":1.0}},"Bernalillo|249":{"county":"Bernalillo","precinct":249,"counts":{"STACEY DEANNE RICH":49,"CYNTHIA D BORREGO":131},"suppressed":[],"party_totals":{"R":49,"D":131},"total":180,"winner":{"R":"STACEY DEANNE RICH","D":"CYNTHIA D BORREGO"},"margin":{"R":1.0,"D":1.0}},"Bernalillo|605":{"county":"Bernalillo","precinct":605,"counts":{"STACEY DEANNE RICH":35,"CYNTHIA D BORREGO":68},"suppressed":[],"party_totals":{"R":35,"D":68},"total":103,"winner":{"R":"STACEY DEANNE RICH","D":"CYNTHIA D BORREGO"},"margin":{"R":1.0,"D":1.0}},"Bernalillo|610":{"county":"Bernalillo","precinct":610,"counts":{"STACEY DEANNE RICH":24,"CYNTHIA D BORREGO":66},"suppressed":[],"party_totals":{"R":24,"D":66},"total":90,"winner":{"R":"STACEY DEANNE RICH","D":"CYNTHIA D BORREGO"},"margin":{"R":1.0,"D":1.0}},"Bernalillo|624":{"county":"Bernalillo","precinct":624,"counts":{"STACEY DEANNE RICH":47,"CYNTHIA D BORREGO":102},"suppressed":[],"party_totals":{"R":47,"D":102},"total":149,"winner":{"R":"STACEY DEANNE RICH","D":"CYNTHIA D BORREGO"},"margin":{"R":1.0,"D":1.0}},"Bernalillo|627":{"county":"Bernalillo","precinct":627,"counts":{"STACEY DEANNE RICH":8,"CYNTHIA D BORREGO":47},"suppressed":[],"party_totals":{"R":8,"D":47},"total":55,"winner":{"R":"STACEY DEANNE RICH","D":"CYNTHIA D BORREGO"},"margin":{"R":1.0,"D":1.0}},"Bernalillo|642":{"county":"Bernalillo","precinct":642,"counts":{"STACEY DEANNE RICH":6,"CYNTHIA D BORREGO":67},"suppressed":[],"party_totals":{"R":6,"D":67},"total":73,"winner":{"R":"STACEY DEANNE RICH","D":"CYNTHIA D BORREGO"},"margin":{"R":1.0,"D":1.0}},"Bernalillo|645":{"county":"Bernalillo","precinct":645,"counts":{"STACEY DEANNE RICH":23,"CYNTHIA D BORREGO":65},"suppressed":[],"party_totals":{"R":23,"D":65},"total":88,"winner":{"R":"STACEY DEANNE RICH","D":"CYNTHIA D BORREGO"},"margin":{"R":1.0,"D":1.0}},"Bernalillo|647":{"county":"Bernalillo","precinct":647,"counts":{"STACEY DEANNE RICH":27,"CYNTHIA D BORREGO":39},"suppressed":[],"party_totals":{"R":27,"D":39},"total":66,"winner":{"R":"STACEY DEANNE RICH","D":"CYNTHIA D BORREGO"},"margin":{"R":1.0,"D":1.0}},"Bernalillo|686":{"county":"Bernalillo","precinct":686,"counts":{"STACEY DEANNE RICH":41,"CYNTHIA D BORREGO":60},"suppressed":[],"party_totals":{"R":41,"D":60},"total":101,"winner":{"R":"STACEY DEANNE RICH","D":"CYNTHIA D BORREGO"},"margin":{"R":1.0,"D":1.0}}}}